[
  {
    "id": "delta-34-pk0",
    "type": "romeo-907",
    "name": "hotel-773",
    "editor_type": "victor-305",
    "html": "yankee-813",
    "text": "victor-958",
    "amp": "hotel-623",
    "created": "kilo-316",
    "updated": "2024-01-01T00:00:00Z"
  },
  {
    "id": "juliet-1-pk1",
    "type": "foxtrot-435",
    "name": "charlie-266",
    "editor_type": "tango-760",
    "html": "hotel-902",
    "text": "oscar-501",
    "amp": "sierra-587",
    "created": "lima-724",
    "updated": "2024-01-01T01:00:00Z"
  },
  {
    "id": "whiskey--pk2",
    "type": "oscar-449",
    "name": "victor-920",
    "editor_type": "india-538",
    "html": "tango-398",
    "text": "golf-186",
    "amp": "golf-817",
    "created": "victor-506",
    "updated": "2024-01-01T02:00:00Z"
  },
  {
    "id": "yankee-2-pk3",
    "type": "yankee-784",
    "name": "yankee-952",
    "editor_type": "xray-397",
    "html": "papa-953",
    "text": "papa-778",
    "amp": "zulu-521",
    "created": "echo-514",
    "updated": "2024-01-01T03:00:00Z"
  },
  {
    "id": "hotel-38-pk4",
    "type": "tango-141",
    "name": "charlie-857",
    "editor_type": "papa-955",
    "html": "hotel-305",
    "text": "charlie-425",
    "amp": "sierra-767",
    "created": "victor-341",
    "updated": "2024-01-01T04:00:00Z"
  },
  {
    "id": "bravo-73-pk5",
    "type": "oscar-320",
    "name": "sierra-358",
    "editor_type": "mike-504",
    "html": "quebec-661",
    "text": "victor-681",
    "amp": "oscar-796",
    "created": "alpha-604",
    "updated": "2024-01-01T05:00:00Z"
  },
  {
    "id": "india-16-pk6",
    "type": "quebec-865",
    "name": "charlie-364",
    "editor_type": "charlie-884",
    "html": "alpha-875",
    "text": "bravo-941",
    "amp": "november-306",
    "created": "romeo-195",
    "updated": "2024-01-01T06:00:00Z"
  },
  {
    "id": "lima-973-pk7",
    "type": "uniform-992",
    "name": "tango-434",
    "editor_type": "foxtrot-521",
    "html": "oscar-596",
    "text": "foxtrot-438",
    "amp": "juliet-793",
    "created": "hotel-693",
    "updated": "2024-01-01T07:00:00Z"
  }
]
